{"errorCode":0,"errorMessage":"","watchTime":0.0,"result":[{"id":1299276,"type":"santu","thumbnails":["https://imgs.gamersky.com/upimg/2020/202006241459067276.jpg","https://imgs.gamersky.com/upimg/2020/202006241459211952.jpg","https://imgs.gamersky.com/upimg/2020/202006241459264026.jpg"],"contentType":"news","contentURL":"","contentId":1299276,"authorHeadImageURL":"","commentsCount":17,"Title":"今日快乐源泉：猫咪蹭痒翻车 幸好我练过瑜伽","Author":"未知","ThumbnailsPicUrl":"","updateTime":"2020-06-24T17:20:48","mark":""},{"id":1298525,"type":"santu","thumbnails":["https://imgs.gamersky.com/upimg/2020/202006220952535462.jpg","https://imgs.gamersky.com/upimg/2020/202006220952585182.jpg","https://imgs.gamersky.com/upimg/2020/202006220953047057.jpg"],"contentType":"news","contentURL":"","contentId":1298525,"authorHeadImageURL":"","commentsCount":21,"Title":"今日快乐源泉：发现猫咪不得了画面 会不会被灭口？","Author":"未知","ThumbnailsPicUrl":"","updateTime":"2020-06-22T19:41:20","mark":""},{"id":1298361,"type":"santu","thumbnails":["https://imgs.gamersky.com/upimg/2020/202006201507138887.jpg","https://imgs.gamersky.com/upimg/2020/202006201507186670.jpg","https://imgs.gamersky.com/upimg/2020/202006201507221007.jpg"],"contentType":"news","contentURL":"","contentId":1298361,"authorHeadImageURL":"","commentsCount":29,"Title":"今日快乐源泉：硬核溜鹅 不仅腿强还得翅膀硬","Author":"未知","ThumbnailsPicUrl":"","updateTime":"2020-06-20T16:43:04","mark":""},{"id":1297815,"type":"santu","thumbnails":["https://imgs.gamersky.com/upimg/2020/202006181755157232.jpg","https://imgs.gamersky.com/upimg/2020/202006181755199144.jpg","https://imgs.gamersky.com/upimg/2020/202006181755247493.jpg"],"contentType":"news","contentURL":"","contentId":1297815,"authorHeadImageURL":"","commentsCount":13,"Title":"今日快乐源泉：有些零食包装就是为了气你 松鼠暴躁","Author":"未知","ThumbnailsPicUrl":"","updateTime":"2020-06-18T19:42:32","mark":""},{"id":1297137,"type":"santu","thumbnails":["https://imgs.gamersky.com/upimg/2020/202006161812471451.jpg","https://imgs.gamersky.com/upimg/2020/202006161812524414.jpg","https://imgs.gamersky.com/upimg/2020/202006161812572125.jpg"],"contentType":"news","contentURL":"","contentId":1297137,"authorHeadImageURL":"","commentsCount":18,"Title":"今日快乐源泉：洗头还有猫咪特别服务？务必让我去","Author":"未知","ThumbnailsPicUrl":"","updateTime":"2020-06-16T20:11:01","mark":""},{"id":1296446,"type":"santu","thumbnails":["https://imgs.gamersky.com/upimg/2020/202006131807435794.jpg","https://imgs.gamersky.com/upimg/2020/202006131807485670.jpg","https://imgs.gamersky.com/upimg/2020/202006131807538510.jpg"],"contentType":"news","contentURL":"","contentId":1296446,"authorHeadImageURL":"","commentsCount":29,"Title":"今日快乐源泉：猫咪高手过招 唯快不破","Author":"未知","ThumbnailsPicUrl":"","updateTime":"2020-06-14T16:49:17","mark":""},{"id":1296196,"type":"santu","thumbnails":["https://imgs.gamersky.com/upimg/2020/202006121744087678.jpg","https://imgs.gamersky.com/upimg/2020/202006121744136824.jpg","https://imgs.gamersky.com/upimg/2020/202006121744185792.jpg"],"contentType":"news","contentURL":"","contentId":1296196,"authorHeadImageURL":"","commentsCount":30,"Title":"今日快乐源泉：不要乱撩 你还不知道我的力量","Author":"未知","ThumbnailsPicUrl":"","updateTime":"2020-06-13T11:54:50","mark":""},{"id":1295765,"type":"santu","thumbnails":["https://imgs.gamersky.com/upimg/2020/202006111233027321.jpg","https://imgs.gamersky.com/upimg/2020/202006111233066070.jpg","https://imgs.gamersky.com/upimg/2020/202006111233105383.jpg"],"contentType":"news","contentURL":"","contentId":1295765,"authorHeadImageURL":"","commentsCount":19,"Title":"今日快乐源泉：小姐姐撸猫就是不一样 真实爽翻","Author":"未知","ThumbnailsPicUrl":"","updateTime":"2020-06-11T20:00:36","mark":""},{"id":1295055,"type":"santu","thumbnails":["https://imgs.gamersky.com/upimg/2020/202006091810251810.jpg","https://imgs.gamersky.com/upimg/2020/202006091810309671.jpg","https://imgs.gamersky.com/upimg/2020/202006091810359671.jpg"],"contentType":"news","contentURL":"","contentId":1295055,"authorHeadImageURL":"","commentsCount":16,"Title":"今日快乐源泉：二哈卖萌也独特 怎么看也是二大于萌","Author":"未知","ThumbnailsPicUrl":"","updateTime":"2020-06-09T19:28:55","mark":""},{"id":1294386,"type":"santu","thumbnails":["https://imgs.gamersky.com/upimg/2020/202006071401132248.jpg","https://imgs.gamersky.com/upimg/2020/202006071401182374.jpg","https://imgs.gamersky.com/upimg/2020/202006071401259502.jpg"],"contentType":"news","contentURL":"","contentId":1294386,"authorHeadImageURL":"","commentsCount":11,"Title":"今日快乐源泉：万物皆可为师 猫都比你会撩妹","Author":"未知","ThumbnailsPicUrl":"","updateTime":"2020-06-07T20:07:28","mark":""},{"id":1293866,"type":"santu","thumbnails":["https://imgs.gamersky.com/upimg/2020/202006051205196417.jpg","https://imgs.gamersky.com/upimg/2020/202006051205248394.jpg","https://imgs.gamersky.com/upimg/2020/202006051205293735.jpg"],"contentType":"news","contentURL":"","contentId":1293866,"authorHeadImageURL":"","commentsCount":15,"Title":"今日快乐源泉：表面正经的熊水下难料 风景独特","Author":"未知","ThumbnailsPicUrl":"","updateTime":"2020-06-06T11:55:19","mark":""},{"id":1293244,"type":"santu","thumbnails":["https://imgs.gamersky.com/upimg/2020/202006031703099290.jpg","https://imgs.gamersky.com/upimg/2020/202006031703145037.jpg","https://imgs.gamersky.com/upimg/2020/202006031703191625.jpg"],"contentType":"news","contentURL":"","contentId":1293244,"authorHeadImageURL":"","commentsCount":24,"Title":"今日快乐源泉：谁能不害怕兽医？学鸵鸟都没用","Author":"未知","ThumbnailsPicUrl":"","updateTime":"2020-06-03T20:23:11","mark":""},{"id":1292569,"type":"santu","thumbnails":["https://imgs.gamersky.com/upimg/2020/202005311514187031.jpg","https://imgs.gamersky.com/upimg/2020/202005311514246817.jpg","https://imgs.gamersky.com/upimg/2020/202005311514303731.jpg"],"contentType":"news","contentURL":"","contentId":1292569,"authorHeadImageURL":"","commentsCount":27,"Title":"今日快乐源泉：睡一觉长了一身猫 这个狗狗厉害了","Author":"未知","ThumbnailsPicUrl":"","updateTime":"2020-06-01T20:22:36","mark":""},{"id":1292541,"type":"santu","thumbnails":["https://imgs.gamersky.com/upimg/2020/202005301812584092.jpg","https://imgs.gamersky.com/upimg/2020/202005301813047432.jpg","https://imgs.gamersky.com/upimg/2020/202005301813088062.jpg"],"contentType":"news","contentURL":"","contentId":1292541,"authorHeadImageURL":"","commentsCount":20,"Title":"今日快乐源泉：随便一躺就是高难度瑜伽 小姐姐羡慕","Author":"未知","ThumbnailsPicUrl":"","updateTime":"2020-05-30T21:05:07","mark":""},{"id":1292028,"type":"santu","thumbnails":["https://imgs.gamersky.com/upimg/2020/202005281750332584.jpg","https://imgs.gamersky.com/upimg/2020/202005281750381422.jpg","https://imgs.gamersky.com/upimg/2020/202005281750436112.jpg"],"contentType":"news","contentURL":"","contentId":1292028,"authorHeadImageURL":"","commentsCount":20,"Title":"今日快乐源泉：想堵住猫咪？灵魂走位感受下","Author":"未知","ThumbnailsPicUrl":"","updateTime":"2020-05-28T20:06:43","mark":""},{"id":1291549,"type":"santu","thumbnails":["https://imgs.gamersky.com/upimg/2020/202005261831108756.jpg","https://imgs.gamersky.com/upimg/2020/202005261831152979.jpg","https://imgs.gamersky.com/upimg/2020/202005261831203423.jpg"],"contentType":"news","contentURL":"","contentId":1291549,"authorHeadImageURL":"","commentsCount":26,"Title":"今日快乐源泉：猫咪实力演绎钢管舞 真大佬无压力","Author":"未知","ThumbnailsPicUrl":"","updateTime":"2020-05-26T19:16:04","mark":""},{"id":1291081,"type":"santu","thumbnails":["https://imgs.gamersky.com/upimg/2020/202005251212343057.jpg","https://imgs.gamersky.com/upimg/2020/202005251212392047.jpg","https://imgs.gamersky.com/upimg/2020/202005251212449414.jpg"],"contentType":"news","contentURL":"","contentId":1291081,"authorHeadImageURL":"","commentsCount":21,"Title":"今日快乐源泉：就不能换个嘴大的来？就光看着","Author":"未知","ThumbnailsPicUrl":"","updateTime":"2020-05-25T19:50:23","mark":""},{"id":1290739,"type":"santu","thumbnails":["https://imgs.gamersky.com/upimg/2020/202005231825528910.jpg","https://imgs.gamersky.com/upimg/2020/202005231825578113.jpg","https://imgs.gamersky.com/upimg/2020/202005231826018116.jpg"],"contentType":"news","contentURL":"","contentId":1290739,"authorHeadImageURL":"","commentsCount":15,"Title":"今日快乐源泉：这狗本体是个气球？不拴着真飞了","Author":"未知","ThumbnailsPicUrl":"","updateTime":"2020-05-24T19:37:13","mark":""},{"id":1290629,"type":"santu","thumbnails":["https://imgs.gamersky.com/upimg/2020/202005221715493212.jpg","https://imgs.gamersky.com/upimg/2020/202005221715558110.jpg","https://imgs.gamersky.com/upimg/2020/202005221716002603.jpg"],"contentType":"news","contentURL":"","contentId":1290629,"authorHeadImageURL":"","commentsCount":28,"Title":"今日快乐源泉：美女小姐姐要喂我吃饭？为啥吃不到","Author":"未知","ThumbnailsPicUrl":"","updateTime":"2020-05-23T21:57:04","mark":""},{"id":1290304,"type":"santu","thumbnails":["https://imgs.gamersky.com/upimg/2020/202005211534546202.jpg","https://imgs.gamersky.com/upimg/2020/202005211534595340.jpg","https://imgs.gamersky.com/upimg/2020/202005211535039071.jpg"],"contentType":"news","contentURL":"","contentId":1290304,"authorHeadImageURL":"","commentsCount":21,"Title":"今日快乐源泉：二哈遇到强劲对手 这腿不是我的","Author":"未知","ThumbnailsPicUrl":"","updateTime":"2020-05-21T21:46:09","mark":""}]}